{
  "version": "1.0.0",
  "description": "12-factor evaluation framework for solo / part-time project ideas. Each factor is scored 1-5 against the rubric anchors. Weights define the Balanced ranking mode; other modes use their own weight vectors in modes.json.",
  "factors": [
    {
      "id": "demand_evidence",
      "name": "Demand Evidence",
      "weight": 14,
      "direction": "up",
      "description": "How strong is the evidence that people actually pay for this? Named competitor with public MRR beats generic category claims.",
      "rubric": {
        "1": "Pure speculation. No named competitors, no traction data.",
        "2": "Adjacent products exist but no direct proof of paid users.",
        "3": "Direct competitors exist with indirect revenue signals (app store presence, funding).",
        "4": "Direct competitors with known public revenue figures (blog posts, press, public MRR).",
        "5": "Concrete named competitor with >$1K MRR publicly cited in the research sources, plus a clear 'X made Y in Z' data point."
      }
    },
    {
      "id": "build_effort",
      "name": "Build Effort",
      "weight": 12,
      "direction": "down",
      "description": "Inverted: less effort = higher score. Solo part-time builders cannot absorb 400h projects.",
      "rubric": {
        "1": "More than 400h to v0.1.",
        "2": "250-400h.",
        "3": "150-250h.",
        "4": "80-150h.",
        "5": "Less than 80h."
      }
    },
    {
      "id": "technical_fit",
      "name": "Technical Fit",
      "weight": 11,
      "direction": "up",
      "description": "How closely does the required stack match the user's existing comfort stack (from profile.yaml).",
      "rubric": {
        "1": "Completely new stack (different language or runtime).",
        "2": "New framework in a familiar language (e.g. React Native when user only knows web React).",
        "3": "Mostly familiar with 1-2 new dependencies.",
        "4": "Pure match with the user's existing stack.",
        "5": "Extends an app the user has already shipped — direct code reuse possible."
      }
    },
    {
      "id": "distribution_clarity",
      "name": "Distribution Clarity",
      "weight": 10,
      "direction": "up",
      "description": "Is there a clear channel to reach customers? Platform-native stores (Chrome Web Store, Figma Community, Raycast) score highest because discovery is built in.",
      "rubric": {
        "1": "Pure 'build it and they will come' — no channel identified.",
        "2": "SEO + content marketing only, long-tail play.",
        "3": "One clear channel (Reddit, X, Product Hunt) but highly competitive.",
        "4": "Platform-native store provides built-in discovery.",
        "5": "Platform-native store plus an existing audience the user already reaches."
      }
    },
    {
      "id": "asset_leverage",
      "name": "Asset Leverage",
      "weight": 10,
      "direction": "up",
      "description": "How much of the user's existing assets (Replit apps, code, IP, audience) does this project reuse?",
      "rubric": {
        "1": "Zero reuse — starts from scratch.",
        "2": "Reuses general skills only.",
        "3": "Reuses specific patterns / snippets from existing apps.",
        "4": "Extends a specific existing Replit app.",
        "5": "Direct v2 of an existing Replit app (AniRec, weight-game, ThesPlan, etc.)."
      }
    },
    {
      "id": "time_to_first_revenue",
      "name": "Time-to-First-Revenue",
      "weight": 9,
      "direction": "up",
      "description": "How fast can this reach its first paid customer? Fast validation beats theoretical upside for solo builders.",
      "rubric": {
        "1": "More than 4 months to first paid user (complex B2B sales cycles).",
        "2": "2-4 months (requires a dedicated marketing push).",
        "3": "1-2 months (paid freemium conversion funnel).",
        "4": "2-4 weeks (platform-native instant-checkout stores).",
        "5": "Less than 2 weeks (pre-orders, waitlist monetization, instant ship on store)."
      }
    },
    {
      "id": "tam",
      "name": "TAM (Total Addressable Market)",
      "weight": 7,
      "direction": "up",
      "description": "Rough global market size estimate. Solo can live in $100M niches; larger TAM is a bonus, not a requirement.",
      "rubric": {
        "1": "Less than $10M globally.",
        "2": "$10M to $100M.",
        "3": "$100M to $500M.",
        "4": "$500M to $2B.",
        "5": "More than $2B globally."
      }
    },
    {
      "id": "competition_density",
      "name": "Competition Density",
      "weight": 7,
      "direction": "curve",
      "description": "Curve score: middle is best. 0 competitors = no market. 30+ competitors = commoditized. Sweet spot is 7-12 direct competitors.",
      "rubric": {
        "1": "Zero competitors (no validated market) OR more than 30 (commoditized).",
        "2": "1-2 competitors, OR 20-30 competitors.",
        "3": "3 competitors, OR 15-20 competitors.",
        "4": "4-6 competitors, OR 12-15 competitors.",
        "5": "7-12 competitors — the sweet spot: validated demand with room to differentiate."
      }
    },
    {
      "id": "moat",
      "name": "Moat",
      "weight": 6,
      "direction": "up",
      "description": "How hard is this to copy after launch? Less critical for portfolio strategy than for a single defensible bet.",
      "rubric": {
        "1": "Pure wrapper anyone can copy in a weekend.",
        "2": "Wrapper plus some custom logic.",
        "3": "Custom data or workflow integration that would take weeks to replicate.",
        "4": "Network effects OR data accumulation OR deep vertical integration.",
        "5": "Multiple of the above plus high switching costs."
      }
    },
    {
      "id": "pricing_power",
      "name": "Pricing Power",
      "weight": 5,
      "direction": "up",
      "description": "What price can this command? Commodity pricing leaves no margin; premium pricing requires a strong wedge.",
      "rubric": {
        "1": "Free only, ad-supported.",
        "2": "€3 to €5 per month (commodity).",
        "3": "€7 to €15 per month (standard SaaS).",
        "4": "€20 to €50 per month (prosumer or small B2B).",
        "5": "€50+ per month (vertical B2B, enterprise-lite)."
      }
    },
    {
      "id": "differentiator",
      "name": "Differentiator Strength",
      "weight": 5,
      "direction": "up",
      "description": "Does this have a unique angle, or is it a me-too?",
      "rubric": {
        "1": "Me-too, no unique angle.",
        "2": "One small improvement over competitors.",
        "3": "Clear unique angle.",
        "4": "Unique angle plus a skill-based or asset-based moat that is hard to copy.",
        "5": "Category-defining wedge — the new thing no one has built yet."
      }
    },
    {
      "id": "operational_burden",
      "name": "Operational Burden",
      "weight": 4,
      "direction": "down",
      "description": "Inverted: less burden = higher score. Solo builders cannot sustain 24/7 support or heavy compliance work.",
      "rubric": {
        "1": "24/7 support needed, compliance-heavy, enterprise sales.",
        "2": "High-touch support and account management required.",
        "3": "Standard SaaS support plus occasional updates.",
        "4": "Light SaaS, mostly automated, minimal support.",
        "5": "Fire-and-forget — one-time purchase, no backend, no ongoing support."
      }
    }
  ]
}
